simplifyline_pybind.cp37-win_amd64.pyd
simplifyline/__init__.py
simplifyline/helper.py
simplifyline-0.0.7.dist-info/LICENSE
simplifyline-0.0.7.dist-info/METADATA
simplifyline-0.0.7.dist-info/WHEEL
simplifyline-0.0.7.dist-info/top_level.txt
simplifyline-0.0.7.dist-info/RECORD
