Metadata-Version: 2.1
Name: simplifyline
Version: 0.0.7
Summary: Simplify 2D and 3D Lines
Home-page: https://github.com/JeremyBYU/cpp-pybind-skel
Author: Jeremy Castagno
Author-email: jeremybyu@gmail.com
License: MIT
Keywords: line 2D 3D simplify simplification
Platform: UNKNOWN
Requires-Dist: numpy (>=1.15.0)
